<?xml version="1.0" encoding="UTF-8"?>
<objects serializationModel="Studio.02.01.00">
	<object class="AudioFile" id="{4a76b0ed-451c-49c3-85dd-5a3b2f44a5e8}">
		<property name="assetPath">
			<value>Whale/Whale Call High (echo) 14.wav</value>
		</property>
		<property name="frequencyInKHz">
			<value>96</value>
		</property>
		<property name="channelCount">
			<value>2</value>
		</property>
		<property name="length">
			<value>5.4613333333333332</value>
		</property>
		<relationship name="masterAssetFolder">
			<destination>{006a0af2-fde3-42f0-b397-dbcc4d039a1b}</destination>
		</relationship>
	</object>
</objects>
