<?xml version="1.0" encoding="UTF-8"?>
<objects serializationModel="Studio.02.01.00">
	<object class="AudioFile" id="{5343e0e1-ecb0-45e7-8249-d5367ccd91d1}">
		<property name="assetPath">
			<value>Sandstorm/Falling debris/Bluezone-BC0197-falling-metal-debris-012.wav</value>
		</property>
		<property name="frequencyInKHz">
			<value>44.0999985</value>
		</property>
		<property name="channelCount">
			<value>2</value>
		</property>
		<property name="length">
			<value>2.7892517006802722</value>
		</property>
		<relationship name="masterAssetFolder">
			<destination>{006a0af2-fde3-42f0-b397-dbcc4d039a1b}</destination>
		</relationship>
	</object>
</objects>
