<?xml version="1.0" encoding="UTF-8"?>
<objects serializationModel="Studio.02.01.00">
	<object class="AudioFile" id="{5b85be24-a10a-44fe-abe6-790aa41623e3}">
		<property name="assetPath">
			<value>SandShift/flowing sand 1.wav</value>
		</property>
		<property name="frequencyInKHz">
			<value>48</value>
		</property>
		<property name="channelCount">
			<value>1</value>
		</property>
		<property name="length">
			<value>1.4304166666666667</value>
		</property>
		<relationship name="masterAssetFolder">
			<destination>{006a0af2-fde3-42f0-b397-dbcc4d039a1b}</destination>
		</relationship>
	</object>
</objects>
